mesogate_router/__init__.py
mesogate_router/main.py
mesogate_router-0.0.0.dist-info/METADATA
mesogate_router-0.0.0.dist-info/WHEEL
mesogate_router-0.0.0.dist-info/licenses/LICENSE
mesogate_router-0.0.0.dist-info/RECORD
